Metadata-Version: 2.1
Name: pyalvarockcl
Version: 1.29
Summary: version 1.29
Home-page: https://github.com/DataBeamCL/pyalvarockcl
Author: Alvaro Fuentes
Author-email: alvarofue@gmail.com
License: Apache 2.0
Keywords: test lib
Platform: UNKNOWN
Classifier: Programming Language :: Python :: 3.10
